aiindex/__init__.py
aiindex/cli.py
aiindex/client.py
aiindex/crypto.py
aiindex/generator.py
aiindex/publisher.py
aiindex/receipts.py
aiindex/signer.py
aiindex/types.py
aiindex/validator.py
aiindex_sdk-1.0.0.dist-info/LICENSE
aiindex_sdk-1.0.0.dist-info/METADATA
aiindex_sdk-1.0.0.dist-info/WHEEL
aiindex_sdk-1.0.0.dist-info/entry_points.txt
aiindex_sdk-1.0.0.dist-info/top_level.txt
aiindex_sdk-1.0.0.dist-info/RECORD
