Metadata-Version: 2.1
Name: aiindex-sdk
Version: 1.0.0
Summary: Python SDK for the AIIndex Protocol - AI-readable website metadata and access control
Home-page: https://github.com/aiindex/aiindex
Author: AIIndex
Author-email: contact@aiindex.org
License: MIT
Project-URL: Documentation, https://aiindex.org/docs
Project-URL: Source, https://github.com/aiindex/aiindex
Project-URL: Bug Reports, https://github.com/aiindex/aiindex/issues
Keywords: ai,indexing,metadata,schema,crawling,web scraping,api
Platform: UNKNOWN
Classifier: Development Status :: 4 - Beta
Classifier: Intended Audience :: Developers
Classifier: License :: OSI Approved :: MIT License
Classifier: Programming Language :: Python :: 3
Classifier: Programming Language :: Python :: 3.8
Classifier: Programming Language :: Python :: 3.9
Classifier: Programming Language :: Python :: 3.10
Classifier: Programming Language :: Python :: 3.11
Classifier: Programming Language :: Python :: 3.12
Classifier: Topic :: Internet :: WWW/HTTP
Classifier: Topic :: Software Development :: Libraries :: Python Modules
Classifier: Topic :: Text Processing :: Markup :: HTML
Requires-Python: >=3.8
License-File: LICENSE
Requires-Dist: requests (>=2.31.0)
Requires-Dist: beautifulsoup4 (>=4.12.0)
Requires-Dist: cryptography (>=41.0.0)
Requires-Dist: click (>=8.1.0)
Requires-Dist: jsonschema (>=4.19.0)
Requires-Dist: pydantic (>=2.0.0)
Requires-Dist: email-validator (>=2.0.0)
Requires-Dist: flask (>=3.0.0)
Requires-Dist: ecdsa (>=0.18.0)
Requires-Dist: python-dateutil (>=2.8.0)
Requires-Dist: lxml (>=4.9.0)
